videoconcat/LICENSE
videoconcat/README.MD
videoconcat/__init__.py
videoconcat/requirements.txt
videoconcat/thirdparty.json
videoconcat-0.11.dist-info/LICENSE.rst
videoconcat-0.11.dist-info/METADATA
videoconcat-0.11.dist-info/WHEEL
videoconcat-0.11.dist-info/top_level.txt
videoconcat-0.11.dist-info/RECORD
